router_movistar/__init__.py
router_movistar/client.py
router_movistar/endpoints.py
router_movistar/extractor.py
router_movistar/model.py
router_movistar-1.0.3.dist-info/METADATA
router_movistar-1.0.3.dist-info/WHEEL
router_movistar-1.0.3.dist-info/top_level.txt
router_movistar-1.0.3.dist-info/RECORD
