Metadata-Version: 2.1
Name: router_movistar
Version: 1.0.3
Summary: A package to extract information from Movistar routers
Home-page: https://github.com/Eitol/router_movistar
Author: Hector Oliveros
Author-email: hector.oliveros.leon@gmail.com
License: MIT
Classifier: Programming Language :: Python :: 3
Classifier: License :: OSI Approved :: MIT License
Classifier: Operating System :: OS Independent
Requires-Python: >=3.12
Requires-Dist: requests ~=2.31.0
Requires-Dist: pydantic ~=2.7.1
